mratools/__init__.py
mra_tools-0.0.1.dist-info/LICENSE
mra_tools-0.0.1.dist-info/METADATA
mra_tools-0.0.1.dist-info/WHEEL
mra_tools-0.0.1.dist-info/top_level.txt
mra_tools-0.0.1.dist-info/RECORD
