Metadata-Version: 2.1
Name: mra-tools
Version: 0.0.1
Summary: GIS Quality Assurance Tools for Mountain Rescue Association
Author-email: Andrey Shmakov <akshmakov@gmail.com>
License: Copyright 2022 MRA Mapping Team Contributors        
Project-URL: Homepage, https://github.com/mra-mapping/mra-tools
Project-URL: Bug Tracker, https://github.com/mra-mapping/mra-tools/issues
Classifier: Programming Language :: Python :: 3
Classifier: License :: OSI Approved :: MIT License
Classifier: Operating System :: OS Independent
Requires-Python: >=3.7
License-File: LICENSE
